<annotation>
	<folder>basketball_images</folder>
	<filename>basketball_54.jpg</filename>
	<path>C:\Courses\TensorFlow_ObjectDetection\models\research\object_detection\basketball_images\basketball_54.jpg</path>
	<source>
		<database>Unknown</database>
	</source>
	<size>
		<width>300</width>
		<height>168</height>
		<depth>3</depth>
	</size>
	<segmented>0</segmented>
	<object>
		<name>basketball</name>
		<pose>Unspecified</pose>
		<truncated>0</truncated>
		<difficult>0</difficult>
		<bndbox>
			<xmin>141</xmin>
			<ymin>17</ymin>
			<xmax>154</xmax>
			<ymax>29</ymax>
		</bndbox>
	</object>
</annotation>
